pyaudioaugment/__init__.py
pyaudioaugment/main_ui.py
pyaudioaugment-1.0.0.dist-info/METADATA
pyaudioaugment-1.0.0.dist-info/WHEEL
pyaudioaugment-1.0.0.dist-info/entry_points.txt
pyaudioaugment-1.0.0.dist-info/top_level.txt
pyaudioaugment-1.0.0.dist-info/RECORD
