Metadata-Version: 2.1
Name: pyaudioaugment
Version: 1.0.0
Requires-Dist: librosa ==0.10.1
Requires-Dist: soundfile ==0.12.1
Requires-Dist: audiomentations ==0.34.1
Requires-Dist: PyQt5
